{
  "@context" : "http://iiif.io/api/presentation/2/context.json",
  "@id" : "https://laura-deluca.github.io/dhsi-2024-inclass/manifests/Hamlet.manifest.json",
  "@type" : "sc:Manifest",
  "label" : "Hamlet by William Shakespeare",
  "metadata" : [ ],
  "description" : [ {
    "@value" : "Hamlet from Shakespeare's Fourth Folio",
    "@language" : "en"
  } ],
  "license" : "https://creativecommons.org/licenses/by/3.0/",
  "attribution" : "William Shakespeare",
  "sequences" : [ {
    "@id" : "http://620dd215-d8db-4768-a4f9-d18e5dddf64d",
    "@type" : "sc:Sequence",
    "label" : [ {
      "@value" : "Normal Sequence",
      "@language" : "en"
    } ],
    "canvases" : [ {
      "@id" : "http://ef401793-14ac-4797-94f1-afdad1948548",
      "@type" : "sc:Canvas",
      "label" : "Empty canvas",
      "height" : 1536,
      "width" : 1030,
      "images" : [ {
        "@context" : "http://iiif.io/api/presentation/2/context.json",
        "@id" : "http://fcc631e9-4b53-4ce9-b913-2c3136d0224e",
        "@type" : "oa:Annotation",
        "motivation" : "sc:painting",
        "resource" : {
          "@id" : "https://laura-deluca.github.io/dhsi-2024-inclass/images/Hamlet/full/full/0/default.jpg",
          "@type" : "dctypes:Image",
          "format" : "image/jpeg",
          "service" : {
            "@context" : "http://iiif.io/api/image/2/context.json",
            "@id" : "https://laura-deluca.github.io/dhsi-2024-inclass/images/Hamlet",
            "profile" : "http://iiif.io/api/image/2/level0.json"
          },
          "height" : 1536,
          "width" : 1030
        },
        "on" : "http://ef401793-14ac-4797-94f1-afdad1948548"
      } ],
      "related" : ""
    } ]
  } ],
  "structures" : [ ]
}